uvvispy/__init__.py
uvvispy/analysis.py
uvvispy/dataset.py
uvvispy/io.py
uvvispy/metadata.py
uvvispy/plotting.py
uvvispy/processing.py
uvvispy-0.1.1.dist-info/LICENSE
uvvispy-0.1.1.dist-info/METADATA
uvvispy-0.1.1.dist-info/WHEEL
uvvispy-0.1.1.dist-info/top_level.txt
uvvispy-0.1.1.dist-info/RECORD
