Metadata-Version: 2.1
Name: uvvispy
Version: 0.1.1
Summary: Package for handling optical absorption data.
Home-page: https://www.uvvispy.de/
Author: Till Biskup
Author-email: till@till-biskup.de
License: UNKNOWN
Project-URL: Documentation, https://docs.uvvispy.de/
Project-URL: Source, https://github.com/tillbiskup/uvvispy
Keywords: spectroscopy,optical spectroscopy,UV-visible spectroscopy,uvvis,data processing and analysis,reproducible science,reproducible research,good scientific practice,recipe-driven data analysis
Platform: UNKNOWN
Classifier: Programming Language :: Python :: 3
Classifier: Programming Language :: Python :: 3.5
Classifier: Programming Language :: Python :: 3.6
Classifier: Programming Language :: Python :: 3.7
Classifier: Programming Language :: Python :: 3.8
Classifier: Programming Language :: Python :: 3.9
Classifier: License :: OSI Approved :: BSD License
Classifier: Operating System :: OS Independent
Classifier: Intended Audience :: Science/Research
Classifier: Development Status :: 4 - Beta
Classifier: Topic :: Scientific/Engineering
Requires-Python: >=3.5
Requires-Dist: aspecd (>=0.2.2)
Provides-Extra: dev
Requires-Dist: prospector ; extra == 'dev'
Provides-Extra: docs
Requires-Dist: sphinx ; extra == 'docs'
Requires-Dist: sphinx-rtd-theme ; extra == 'docs'
